Workbook

Sheet Resumen
A1: CUADRE DE DEPÓSITOS Y GASTOS — Activación Fresko Cumbres, Monterrey (sep 2026)
A4: 1. LO QUE ME DEPOSITARON | B4: Monto
A5: Total depósitos | B5: =Depositos!E24 -> 294350
A6: Con comprobante | B6: =Depositos!E25 -> 294350
A7: Sin comprobante (pedir a Aldo / Tere) | B7: =Depositos!E26 -> 0
A9: 2. EN QUÉ SE GASTÓ | B9: Monto
A10: Macetas | B10: =SUMIF(Gastos!B5:B28,"Macetas",Gastos!F5:F28) -> 43200
A11: Mástiles | B11: =SUMIF(Gastos!B5:B28,"Mástiles",Gastos!F5:F28) -> 20745.39
A12: Hospedaje | B12: =SUMIF(Gastos!B5:B28,"Hospedaje",Gastos!F5:F28) -> 15049.5
A13: Nómina | B13: =SUMIF(Gastos!B5:B28,"Nómina",Gastos!F5:F28) -> 30150
A14: Transporte | B14: =SUMIF(Gastos!B5:B28,"Transporte",Gastos!F5:F28) -> 6675.8
A15: Material y herramienta | B15: =SUMIF(Gastos!B5:B28,"Material y herramienta",Gastos!F5:F28) -> 9732.24
A16: Hidratación del equipo (agua, hielo, bebidas) y comidas dentro de Fresko | B16: =SUMIF(Gastos!B5:B28,"Hidratación del equipo (agua, hielo, bebidas) y comidas dentro de Fresko",Gastos!F5:F28) -> 11208.78
A17: Nómina diaria (pestaña Nomina) | B17: =Nomina!E23 -> 129850
A18: Viáticos diarios: Uber, comidas (pestaña Viaticos) | B18: =Viaticos!E27 -> 16265.9
A19: Gasto personal (no Fresko): bicicleta y squishys | B19: =SUMIF(Gastos!B5:B28,"Personal (no Fresko)",Gastos!F5:F28) -> 5000
A20: TOTAL GASTOS | B20: =SUM(B10:B19) -> 287877.61
A22: 3. CUADRE | B22: Monto
A23: Depósitos - Gastos | B23: =B5-B20 -> 6472.39
A24: =IF(B23>0,"Te sobra dinero de Aldo: falta justificar o devolver esta cantidad",IF(B23<0,"Pusiste dinero de tu bolsa: Aldo te debe esta cantidad","Cuadra exacto")) -> Te sobra dinero de Aldo: falta justificar o devolver esta cantidad
A26: 4. PENDIENTES | B26: Cuántos
A27: Gastos sin monto (amarillos en Gastos) | B27: =COUNTBLANK(Gastos!F5:F28) -> 1
A28: Depósitos sin comprobante | B28: =COUNTIF(Depositos!G5:G22,"NO") -> 0
A29: Días de nómina sin capturar | B29: =COUNTBLANK(Nomina!B6:B21) -> 0

Sheet Depositos
A1: DEPÓSITOS RECIBIDOS DE ALDO / TERE / CLAUDIA
A2: Lista enviada por Aldo en el grupo Pop Monterrey el 28 sep. Comprobantes cruzados con capturas BBVA/Santander.
A4: # | B4: Fecha | C4: Quién depositó | D4: Concepto en el banco | E4: Monto | F4: Comprobante (folio) | G4: ¿Tengo comprobante? | H4: Notas
A5: 1 | B5: 2026-08-31 | C5: Aldo | D5: taxi | E5: 350 | F5: BBVA 7181151020 | G5: Sí
A6: 2 | B6: 2026-09-05 | C6: Tere | E6: 10000 | F6: Confirmado en estado de cuenta (Teresita Del Carmen Terrones Velez, 5-sep) | G6: Sí | H6: Ya no falta pedirle el comprobante a Tere; se confirmó en tu estado de cuenta.
A7: 3 | B7: 2026-09-04 | C7: Aldo | D7: mac | E7: 50000 | F7: BBVA 0078243194 | G7: Sí | H7: Macetas $43,200 + $6,800 para mástiles
A8: 4 | B8: 2026-09-05 | C8: Aldo | E8: 10000 | F8: Confirmado en estado de cuenta (Mario Aldo Montenegro Esqueda, 5-sep) | G8: Sí | H8: Los 10 mil de los mástiles; ya se confirmó en tu estado de cuenta.
A9: 5 | B9: 2026-09-09 | C9: Aldo | D9: aldo | E9: 500 | F9: BBVA 0053838352 | G9: Sí
A10: 6 | B10: 2026-09-09 | C10: Aldo | D10: pago | E10: 40000 | F10: BBVA 0056968572 | G10: Sí
A11: 7 | B11: 2026-09-12 | C11: Aldo | D11: monterewy | E11: 20000 | F11: BBVA 8191486766 | G11: Sí
A12: 8 | B12: 2026-09-13 | C12: Aldo | D12: nom | E12: 25000 | F12: BBVA 8295941864 | G12: Sí
A13: 9 | B13: 2026-09-15 | C13: Aldo | E13: 20000 | F13: Confirmado en estado de cuenta (Mario Aldo Montenegro Esqueda, 15-sep) | G13: Sí | H13: Ya se confirmó en tu estado de cuenta.
A14: 10 | B14: 2026-09-17 | C14: Aldo | D14: beto | E14: 15000 | F14: BBVA 8573668813 | G14: Sí
A15: 11 | B15: 2026-09-18 | C15: Aldo | D15: monterrey | E15: 15000 | F15: BBVA 8740024681 | G15: Sí
A16: 12 | B16: 2026-09-19 | C16: Aldo | D16: nom | E16: 8000 | F16: BBVA 8827672930 | G16: Sí
A17: 13 | B17: 2026-09-21 | C17: Aldo | D17: beto | E17: 9900 | F17: BBVA 8916686512 | G17: Sí
A18: 14 | B18: 2026-09-21 | C18: Daniel Maximiliano Morales Sanchez (a nombre de Aldo) | D18: ALBERTO BALDERAS de Aldo | E18: 30000 | F18: Santander 3864634 | G18: Sí | H18: Confirmado: sí se acreditó (estado de cuenta, 21-sep, $30,000). El nombre del remitente en el banco es Daniel Maximiliano Morales Sanchez, a nombre de Aldo; antes tenías anotado 'Claudia'.
A19: 15 | B19: 2026-09-24 | C19: Aldo | D19: beto | E19: 4500 | F19: BBVA 9176305601 | G19: Sí
A20: 16 | B20: 2026-09-25 | C20: Aldo | D20: aldo | E20: 28000 | F20: BBVA 9262072334 | G20: Sí
A21: 17 | B21: 2026-09-25 | C21: Aldo | D21: beto | E21: 3100 | F21: BBVA 9346948390 | G21: Sí
A22: 18 | B22: 2026-09-08 | C22: Daniel Maximiliano Morales Sanchez | E22: 5000 | F22: Confirmado en estado de cuenta (Daniel Maximiliano Morales Sanchez, 8-sep) | G22: Sí | H22: Alberto confirma que este depósito sí es de la activación Fresko Cumbres. por parte de Claudia
D24: TOTAL DEPÓSITOS | E24: =SUM(E5:E22) -> 294350
D25: Con comprobante | E25: =SUMIF(G5:G22,"Sí",E5:E22) -> 294350
D26: Sin comprobante (amarillo) | E26: =SUMIF(G5:G22,"NO",E5:E22) -> 0
D28: Total según la lista de Aldo: $289,350

Sheet Gastos
A1: GASTOS DE LA ACTIVACIÓN (todo menos nómina diaria y viáticos diarios)
A4: # | B4: Categoría | C4: Fecha | D4: Proveedor / Persona | E4: Concepto | F4: Monto | G4: Comprobante | H4: Estatus | I4: Notas
A5: 1 | B5: Macetas | C5: 2026-09-05 | D5: Ricardo Dávila (proveedor) | E5: 3,000 macetas | F5: 43200 | H5: Falta comprobante | I5: Monto según tu mensaje en el grupo 5 sep
A6: 2 | B6: Mástiles | C6: 2026-09-06 | D6: Iván / proveedores | E6: Material 3 mástiles (incluye 20%) | F6: 13830.26 | G6: mastil_v2_fabricacion.pdf | H6: Cotización | I6: Pagado con $6,800 sobrantes de macetas + $10,000 del 5 sep + tu dinero Alberto confirma que ese dinero se lo transfirió a Iván.
A7: 3 | B7: Mástiles | C7: 2026-09-06 | D7: Iván | E7: Mano de obra de herrería 3 mástiles | F7: 6915.13 | G7: mastil_v2_fabricacion.pdf | H7: Cotización | I7: Alberto confirma que el dinero de mástiles se lo transfirió a Iván (mismo pago que fila 6).
A8: 4 | B8: Hospedaje | C8: 2026-09-05 a 09-07 | D8: Airbnb | E8: Airbnb 5 al 7 sep (104 USD) | F8: 1749.5 | G8: Cargo de tarjeta 5-sep 12:59, $1,749.50 (Airbnb * hmzmsbzebz) | H8: Con comprobante | I8: Confirmado con el estado de cuenta: cargo real de $1,749.50 (antes se había estimado $1,857 con un tipo de cambio aproximado; este es el monto exacto que cobró la tarjeta).
A9: 5 | B9: Hospedaje | C9: 2026-09-07 a 09-13 | D9: Hospedaje | E9: Hospedaje 7 al 13 sep | F9: 4200 | G9: Mercado Pago #178194749650 | H9: Con comprobante | I9: Transferencia a Patricia Carolina Martínez, 9-sep 5:15pm, $700 x 6 noches (7-13 sep).
A10: 6 | B10: Hospedaje | C10: 2026-09-18 | D10: Patricia Carolina Martínez | E10: Hospedaje 7 días, hasta el 20 sep | F10: 5600 | G10: Mercado Pago #178802483395 | H10: Con comprobante
A11: 7 | B11: Hospedaje | C11: 2026-09-21 a 09-24 | D11: Hospedaje | E11: Hospedaje 21 al 24 sep | F11: 2100 | G11: Mercado Pago #180505459664 | H11: Con comprobante | I11: Transferencia a Patricia Carolina Martínez, 23-sep 10:45am, $700 x 3 noches (21-24 sep). La nota anterior decía $800/noche; el chat con Carolina confirma que la tarifa real acordada fue $700/noche.
A12: 8 | B12: Hospedaje | C12: 2026-09-25 | D12: Hospedaje | E12: Noche extra (no desalojé el 24) | F12: 1400 | G12: Mercado Pago #179937675245 (1 de 2 transferencias de $700) | H12: Con comprobante parcial | I12: Cubre las noches del 24 y 25-sep ($700 c/u, según el chat con Carolina). Alberto mandó $700 el 25-sep 7:14pm (comprobante #179937675245) y prometió otros $700 en cuanto le depositaran; no hay comprobante de esa segunda transferencia todavía.
A13: 9 | B13: Hospedaje | C13: 2026-09-25 | D13: Hotel | E13: Hotel 25 sep | H13: Duplicado - no contar | I13: Era la misma noche extra de la fila 12 (Carolina cobra por noche, no existe un 'hotel' aparte). Se deja en $0 para no duplicar; los $1,400 completos ya están en la fila 12.
A14: 10 | B14: Nómina | C14: 2026-09-14 | D14: Rolando (sonido) | E14: 8 días x $700 | F14: 5600 | G14: Mercado Pago #179081572804 | H14: Con comprobante | I14: El costo era de 900 se negocio a 700 por distancia.
A15: 11 | B15: Nómina | C15: 2026-09-24 | D15: Promotores | E15: Liquidación final en efectivo (23 y 24 sep): jornada, puntualidad y referidos | F15: 24350 | G15: XLS enviado al grupo 24 sep | H15: Con comprobante | I15: Monto real registrado en el sistema de nómina: $12,250 del 23-sep + $12,100 del 24-sep. El XLS enviado al grupo decía $25,350; la diferencia de $1,000 viene de ajustes posteriores. Con esto, nómina total = $142,800, igual que el archivo de detalle de nómina.
A16: 12 | B16: Transporte | C16: 2026-08-31 | D16: Taxi | E16: Taxi (depósito de $350 del 31 ago) | F16: 350 | H16: Con comprobante | I16: Coincide con el depósito de $350 que Aldo marcó 'taxi' el 31-ago (mismo monto exacto).
A17: 13 | B17: Transporte | C17: 2026-09-07 | D17: Boleto Iván | E17: Boleto de Iván a Monterrey | F17: 1499.27 | G17: Viva Aerobus, cargo de tarjeta 7-sep 23:13 | H17: Con comprobante
A18: 15 | B18: Transporte | C18: 2026-09-25 | D18: Camión | E18: Camión de regreso MTY - CDMX | F18: 1669.5 | G18: Mercado Pago #179936512115 (Autobuses Estrella Blanca) | H18: Con comprobante | I18: Boleto de autobús, Monterrey - México Norte, 25-sep.
A19: 16 | B19: Material y herramienta | C19: 2026-09-09 a 09-22 | D19: Home Depot / Fresko / ferreterías | E19: Tickets Lote 1 (20 tickets) — detalle artículo por artículo en la pestaña 'Detalle tickets' | F19: 9098.24 | G19: Fotos de tickets | H19: Con comprobante | I19: 5 tickets de Home Depot sin fecha visible
A20: 17 | B20: Hidratación del equipo (agua, hielo, bebidas) y comidas dentro de Fresko | C20: 2026-09-10 a 09-23 | D20: Fresko | E20: Tickets Lote 2 (19 tickets) — detalle artículo por artículo en la pestaña 'Detalle tickets' | F20: 2304.64 | G20: Fotos de tickets | H20: Con comprobante
A21: 18 | B21: Hidratación del equipo (agua, hielo, bebidas) y comidas dentro de Fresko | C21: 2026-09-09 a 09-19 | D21: Fresko | E21: Tickets Lote 3 (11 tickets) — detalle artículo por artículo en la pestaña 'Detalle tickets' | F21: 1218.2 | G21: Fotos de tickets | H21: Con comprobante | I21: Corregido a la suma real de los 11 tickets (todos con foto). Antes estaba capturado en $1,238.20.
A22: 19 | B22: Hidratación del equipo (agua, hielo, bebidas) y comidas dentro de Fresko | C22: 2026-09-11 a 09-23 | D22: Fresko | E22: Tickets Lote 4 (16 tickets) — detalle artículo por artículo en la pestaña 'Detalle tickets' | F22: 3701.85 | G22: Fotos de tickets | H22: Con comprobante | I22: Sin contar el retiro de efectivo de $1,500
A23: 20 | B23: Transporte | C23: 2026-09-04 | D23: Viva Aerobus | E23: Vuelo de Alberto a Monterrey | F23: 2357.03 | G23: Viva Aerobus, cargo de tarjeta 4-sep 20:49 | H23: Con comprobante
A24: 21 | B24: Material y herramienta | C24: 2026-09-08 | D24: Elec Steren | E24: Compra en Steren | F24: 634 | G24: Cargo de tarjeta 8-sep 09:07 | H24: Con comprobante | I24: Revisa qué se compró exactamente; no venía en las fotos de tickets de los Lotes.
A25: 22 | B25: Hidratación del equipo (agua, hielo, bebidas) y comidas dentro de Fresko | C25: 2026-09-09 a 09-24 | D25: Fresko Valle Cumbres | E25: Cargos de tarjeta en Fresko Valle Cumbres que no tienen ticket en los lotes (14 de 54) — lista en la pestaña 'Cargos Fresko' | F25: ='Cargos Fresko'!F59 -> 3984.09 | G25: Estado de cuenta de tarjeta, 54 cargos 'Pago en tienda física' | H25: Con comprobante | I25: Estado de cuenta, 9 al 24-sep: 54 cargos por $11,656.88. Se revisaron contra los tickets: 39 cargos ($5,993.74) son las mismas compras que ya están en los tickets de los lotes, y uno ($1,679.05) es el ticket L4-11 más un retiro de efectivo de $1,500. Para no contar dos veces, aquí solo van los 14 cargos restantes.
A26: 22 | B26: Personal (no Fresko) | D26: Alberto | E26: Bicicleta de Emilia y squishys | F26: 5000 | H26: Gasto personal | I26: Gasto personal de Alberto, no es de Fresko.
A27: 23 | B27: Transporte | C27: Último día | D27: Didier | E27: Taxis del último día | F27: 800 | H27: Por pagar | I27: Pendiente de pagarle a Didier.
A28: 24 | B28: Nómina | C28: 2026-09-18 | D28: Karen Lizbeth Jiménez (folio 082) | E28: Saldo de su turno del 18-sep | F28: 200 | H28: Por transferir | I28: Se le entregaron $200 ese día; faltan $200 por transferir.
E29: TOTAL GASTOS (esta pestaña) | F29: =SUM(F5:F28) -> 141761.71

Sheet Nomina
A1: NÓMINA DIARIA (lo que pagaste cada día a los promotores)
F2: Pago por turno | G2: 400 | H2: Dato tuyo: turno $400
A3: Ejemplo: 11 personas x $400 = $4,400 + Didier $800 en Extras = $5,200 ese día.
A5: Fecha | B5: Personas que trabajaron | C5: Turnos (personas x pago) | D5: Extras (Didier, suplentes, bonos) | E5: Total del día | F5: Notas
A6: 46273 | B6: 0 | C6: =B6*$G$2 -> 0 | D6: 6800 | E6: =C6+D6 -> 6800 | F6: 8-sep: capacitación (34 promotores x $200 = $6,800), no hubo turno de calle
A7: 46274 | B7: 22 | C7: =B7*$G$2 -> 8800 | D7: 400 | E7: =C7+D7 -> 9200
A8: 46275 | B8: 26 | C8: =B8*$G$2 -> 10400 | D8: 400 | E8: =C8+D8 -> 10800
A9: 46276 | B9: 23 | C9: =B9*$G$2 -> 9200 | D9: 400 | E9: =C9+D9 -> 9600
A10: 46277 | B10: 27 | C10: =B10*$G$2 -> 10800 | D10: 400 | E10: =C10+D10 -> 11200
A11: 46278 | B11: 34 | C11: =B11*$G$2 -> 13600 | D11: 4850 | E11: =C11+D11 -> 18450 | F11: incluye puntualidad $4,100 + referidos $350 (cierre Etapa 1)
A12: 46279 | B12: 19 | C12: =B12*$G$2 -> 7600 | D12: 400 | E12: =C12+D12 -> 8000
A13: 46280 | B13: 16 | C13: =B13*$G$2 -> 6400 | D13: 800 | E13: =C13+D13 -> 7200 | F13: Didier ya con tarifa $800/día desde este día
A14: 46281 | B14: 0 | C14: =B14*$G$2 -> 0 | D14: 0 | E14: =C14+D14 -> 0 | F14: 16-sep: día de descanso, no se trabajó
A15: 46282 | B15: 18 | C15: =B15*$G$2 -> 7200 | D15: 800 | E15: =C15+D15 -> 8000
A16: 46283 | B16: 19 | C16: =B16*$G$2 -> 7600 | D16: 600 | E16: =C16+D16 -> 8200 | F16: Incluye $200 del turno de Karen (082); le quedan $200 pendientes.
A17: 46284 | B17: 15 | C17: =B17*$G$2 -> 6000 | D17: 0 | E17: =C17+D17 -> 6000 | F17: Didier no fue pagado ese día
A18: 46285 | B18: 21 | C18: =B18*$G$2 -> 8400 | D18: 400 | E18: =C18+D18 -> 8800
A19: 46286 | B19: 22 | C19: =B19*$G$2 -> 8800 | D19: 400 | E19: =C19+D19 -> 9200
A20: 46287 | B20: 14 | C20: =B20*$G$2 -> 5600 | D20: 0 | E20: =C20+D20 -> 5600 | F20: Didier no fue pagado ese día
A21: 46288 | B21: 6 | C21: =B21*$G$2 -> 2400 | D21: 400 | E21: =C21+D21 -> 2800 | F21: Incluye 1 turno del 24-sep (folio 077) pagado aparte de la liquidación.
D23: TOTAL NÓMINA DIARIA | E23: =SUM(E6:E21) -> 129850
A24: La liquidación final (23 y 24 sep) y lo de Rolando ($5,600) ya están en la pestaña Gastos; no los repitas aquí.

Sheet Viaticos
A1: VIÁTICOS DIARIOS (Uber, comidas y otros gastos sin ticket)
A4: Fecha | B4: Uber / taxi | C4: Comidas (sin ticket) | D4: Otros | E4: Total del día | F4: Notas
A5: 46270 | B5: 1000 | C5: 103 | E5: =SUM(B5:D5) -> 1103 | F5: Tacos (mtycasabeneltogo), cargo de tarjeta 5-sep 12:48, $103.
A6: 46271 | E6: =SUM(B6:D6) -> 0 | F6: PENDIENTE: no especificaste Uber de este día, ¿hubo gasto?
A7: 46272 | C7: 299 | D7: 238 | E7: =SUM(B7:D7) -> 537 | F7: Mercado Pago *muchoric, cargo de tarjeta 7-sep 22:08, $299. Otros: Oxxo $238.00.
A8: 46273 | B8: 500 | E8: =SUM(B8:D8) -> 500 | F8: 8-sep: $500, según Alberto.
A9: 46274 | B9: 1600 | D9: 432 | E9: =SUM(B9:D9) -> 2032 | F9: $1,600 según lo que dijiste; de eso, $327.62 ya tiene comprobante real (Uber, cargo de tarjeta 9-sep 23:40). El resto no tiene comprobante todavía. Otros: Oxxo $432.00.
A10: 46275 | B10: 400 | D10: 500 | E10: =SUM(B10:D10) -> 900 | F10: $400 ida y vuelta (10 al 25-sep), según Alberto.
A11: 46276 | B11: 400 | D11: 72 | E11: =SUM(B11:D11) -> 472 | F11: $400 ida y vuelta (10 al 25-sep), según Alberto. Otros: Oxxo $72.00.
A12: 46277 | B12: 400 | D12: 418.5 | E12: =SUM(B12:D12) -> 818.5 | F12: $400 ida y vuelta (10 al 25-sep), según Alberto. Otros: Oxxo $65.00 + Oxxo $199.00 + Oxxo $80.00 + Oxxo $74.50.
A13: 46278 | B13: 400 | D13: 587 | E13: =SUM(B13:D13) -> 987 | F13: $400 ida y vuelta (10 al 25-sep), según Alberto. Otros: 7 Eleven $46.00 + Oxxo $132.00 + Oxxo $409.00.
A14: 46279 | B14: 400 | D14: 120.9 | E14: =SUM(B14:D14) -> 520.9 | F14: $400 ida y vuelta (10 al 25-sep), según Alberto. Otros: Oxxo $120.90.
A15: 46280 | B15: 400 | D15: 208.5 | E15: =SUM(B15:D15) -> 608.5 | F15: $400 ida y vuelta (10 al 25-sep), según Alberto. Otros: 7 Eleven $136.50 + Oxxo $72.00.
A16: 46281 | B16: 400 | D16: 500 | E16: =SUM(B16:D16) -> 900 | F16: $400 ida y vuelta (10 al 25-sep), según Alberto.
A17: 46282 | B17: 400 | D17: 500 | E17: =SUM(B17:D17) -> 900 | F17: $400 ida y vuelta (10 al 25-sep), según Alberto.
A18: 46283 | B18: 400 | D18: 500 | E18: =SUM(B18:D18) -> 900 | F18: $400 ida y vuelta (10 al 25-sep), según Alberto.
A19: 46284 | B19: 400 | D19: 500 | E19: =SUM(B19:D19) -> 900 | F19: $400 ida y vuelta (10 al 25-sep), según Alberto.
A20: 46285 | B20: 400 | D20: 155 | E20: =SUM(B20:D20) -> 555 | F20: $400 ida y vuelta (10 al 25-sep), según Alberto. Otros: 7 Eleven $155.00.
... A25: 46290 | B25: 400 | D25: 214 | E25: =SUM(B25:D25) -> 614 | F25: $400 ida y vuelta (10 al 25-sep), según Alberto. Otros: 7 Eleven $214.00.
D27: TOTAL VIÁTICOS | E27: =SUM(E5:E25) -> 16265.9
A28: Las comidas que tienen ticket de Fresko ya están en Gastos (Lotes 2, 3 y 4); aquí solo lo que no tiene ticket.
A29: Otros: cargos de tarjeta en Oxxo y 7 Eleven (salidas, cenas, etc.), en el día que se hicieron.

Sheet Detalle tickets
A1: DETALLE DE TICKETS — artículo por artículo
A2: Cada ticket aparece en un renglón verde con su total; abajo, lo que se compró. Vale el total impreso en el ticket.
A4: Lote | B4: Ticket | C4: Fecha | D4: Hora | E4: Tienda | F4: Folio / referencia | G4: Pago | H4: Artículo | I4: Cant. | J4: Importe
A5: LOTE 1 · Material y herramienta
A6: 1 | B6: 6 | C6: 2026-09-09 | D6: 14:14 | E6: Fresko | F6: 462 70 4 4882 | G6: Efectivo | H6: TOTAL DEL TICKET | J6: 138
H7: Guante Adir (pieza) | I7: 2 | J7: 84
H8: Guante Osni (par) | I8: 2 | J8: 54
A9: 1 | B9: 7 | C9: 2026-09-09 | D9: 18:47 | E9: Fresko | F9: 462 67 3 4973 / aut 716482 | G9: Tarjeta | H9: TOTAL DEL TICKET | J9: 135.35
H10: Cordel Redac 15 m | I10: 1 | J10: 62.35
H11: Cinta Scotch | I11: 1 | J11: 44
H12: Tubo Sunny | I12: 1 | J12: 29
A13: 1 | B13: 10 | C13: 2026-09-09 | D13: 19:02 | E13: Fresko | F13: 462 8024 22 4928 / aut 742432 | G13: Tarjeta | H13: TOTAL DEL TICKET | J13: 94
H14: Cutter Truper | I14: 1 | J14: 94
A15: 1 | B15: 8 | C15: 2026-09-10 | D15: 20:21 | E15: Fresko | F15: 462 57 8 5250 / aut 691057 | G15: Tarjeta | H15: TOTAL DEL TICKET | J15: 29
H16: Tubo Sunny | I16: 1 | J16: 29
A17: 1 | B17: 20 | C17: 2026-09-11 | D17: 12:35 | E17: Solace Ferretería Leones | F17: Ticket 163403 | G17: Efectivo | H17: TOTAL DEL TICKET | J17: 1331
H18: Mixto por costal 40 kg | I18: 6 | J18: 660
H19: Tensor zinc 5/16" gancho-argolla | I19: 3 | J19: 210
H20: Maniobra a pie de banqueta | I20: 1 | J20: 350
H21: Costal para escombro | I21: 6 | J21: 111
A22: 1 | B22: 14 | C22: 2026-09-11 | D22: 16:47 | E22: Fresko | F22: 462 66 7 5341 / aut 511662 | G22: Tarjeta | H22: TOTAL DEL TICKET | J22: 29
H23: Tubo Sunny | I23: 1 | J23: 29
A24: 1 | B24: 12 | C24: 2026-09-12 | D24: 12:33 | E24: Ferre 2.22 El Nopalero | F24: Folio 47385 | G24: Efectivo | H24: TOTAL DEL TICKET | J24: 277
H25: Abrazadera D | I25: 2 | J25: 25.86
H26: Manguera TRA | I26: 1 | J26: 3.45
H27: Conector ROS | I27: 2 | J27: 13.79
H28: Válvula check | I28: 1 | J28: 195.69
H29: IVA | J29: 38.21
A30: 1 | B30: 3 | C30: 2026-09-12 | D30: 13:33 | E30: Fresko | F30: 462 8019 18 5336 / aut 824514 | G30: Tarjeta | H30: TOTAL DEL TICKET | J30: 144
H31: Desarmador Pretul 4 piezas | I31: 1 | J31: 144
A32: 1 | B32: 5 | C32: 2026-09-13 | D32: 18:36 | E32: Fresko | F32: 462 8023 21 5473 / aut 740845 | G32: Tarjeta | H32: TOTAL DEL TICKET | J32: 321
H33: Extensión Argos | I33: 2 | J33: 258
H34: Chocolate Nestlé | I34: 3 | J34: 63
A35: 1 | B35: 4 | C35: 2026-09-15 | D35: 15:08 | E35: Fresko | F35: 462 41 4 5590 / aut 428564 | G35: Tarjeta | H35: TOTAL DEL TICKET | J35: 179
H36: Candado Philips | I36: 1 | J36: 179
A37: 1 | B37: 13 | C37: 2026-09-15 | D37: 15:16 | E37: Fresko | F37: 462 33 13 6627 / aut 202943 | G37: Tarjeta | H37: TOTAL DEL TICKET | J37: 78
H38: Candado Hermex | I38: 1 | J38: 78
A39: 1 | B39: 18 | C39: 2026-09-17 | D39: 17:06 | E39: Fresko | F39: 462 54 6 6259 / aut 559476 | G39: Tarjeta | H39: TOTAL DEL TICKET | J39: 142
H40: Pintura Politec 6 piezas | I40: 1 | J40: 110
H41: Pinceles pelo de búfalo | I41: 1 | J41: 62
H42: Descuento promoción | J42: -30
A43: 1 | B43: 15 | C43: 2026-09-19 | D43: 19:01 | E43: Fresko | F43: 462 33 10 7605 | G43: Efectivo | H43: TOTAL DEL TICKET | J43: 408.14
H44: Pintura acrílica UE | I44: 1 | J44: 51.9
H45: Pintura acrílica AM | I45: 1 | J45: 51.9
H46: Pintura Fergero 6 piezas | I46: 1 | J46: 150
H47: Pintura Dietrix | I47: 3 | J47: 56.49
H48: Pinceles escolares | I48: 1 | J48: 86
H49: Pastillas Mentos | I49: 1 | J49: 11.85
A50: 1 | B50: 19 | C50: 2026-09-20 | D50: 20:32 | E50: Fresko | F50: 462 8026 24 5661 / aut 103248 | G50: Tarjeta | H50: TOTAL DEL TICKET | J50: 44
H51: Cinta Scotch | I51: 1 | J51: 44
A52: 1 | B52: 16 | C52: 2026-09-22 | D52: 16:00 | E52: Fresko | F52: 462 26 9 7191 / aut 403563 | G52: Tarjeta | H52: TOTAL DEL TICKET | J52: 24
H53: Contacto Argos | I53: 1 | J53: 24
A54: 1 | B54: 1 | C54: Sin fecha | E54: Home Depot Cumbres | F54: Aprobada 368928 | G54: Tarjeta | H54: TOTAL DEL TICKET — Foto cortada: no se ve la fecha | J54: 2688
H55: Tubo PVC C40 1 1/2" | I55: 1 | J55: 46
H56: Tubo PVC C40 1" | I56: 1 | J56: 34
H57: Poliflex naranja | I57: 1 | J57: 109
H58: Rotomartillo Ryobi 5/8" | I58: 1 | J58: 1239
H59: Descuento rotomartillo | J59: -290
H60: Cordón UR 2x14 negro (metros) | I60: 40 | J60: 1420
H61: Snickers 2 pack | I61: 1 | J61: 85
H62: Chips jalapeño | I62: 1 | J62: 45
A63: 1 | B63: 2 | C63: Sin fecha | E63: Home Depot Cumbres | F63: — | G63: Efectivo | H63: TOTAL DEL TICKET — Foto cortada: no se ve la fecha | J63: 780
H64: Tensor ojo-gancho | I64: 4 | J64: 692
H65: Nudo para cable Veke | I65: 4 | J65: 88
A66: 1 | B66: 9 | C66: Sin fecha | E66: Home Depot García | F66: Aprobada 136008 | G66: Tarjeta | H66: TOTAL DEL TICKET — Foto cortada: no se ve la fecha | J66: 138
H67: Tubo PVC C40 1 1/2" | I67: 3 | J67: 138
A68: 1 | B68: 11 | C68: Sin fecha | E68: Home Depot García | F68: Aprobada 367496 | G68: Tarjeta | H68: TOTAL DEL TICKET — Foto cortada: no se ve la fecha | J68: 188
H69: Guardacabo Veker 1/8 | I69: 4 | J69: 68
H70: Tuerca hexagonal GR.5 fina | I70: 1 | J70: 59
H71: Descuento liquidación | J71: -49
H72: Nudo para cable Veke | I72: 5 | J72: 110
A73: 1 | B73: 17 | C73: Sin fecha | E73: Home Depot García | F73: Aprobada 065626 | G73: Tarjeta | H73: TOTAL DEL TICKET — Foto cortada: no se ve la fecha | J73: 1930.75
H74: Válvula de bola 1/2 | I74: 1 | J74: 28.05
H75: Tubo CPVC 1/2 x 1 m | I75: 1 | J75: 14.3
H76: Placa contacto doble | I76: 1 | J76: 65
H77: Semillas hierba alba | I77: 4 | J77: 104
H78: Cemento Flowguard 2 oz | I78: 1 | J78: 57
H79: Clavija blindada 3x1 | I79: 1 | J79: 87
H80: Caja de empotrar | I80: 1 | J80: 14
H81: Cordón UR 2x14 negro (metros) | I81: 36 | J81: 1278
H82: Monster Energy | I82: 2 | J82: 130
H83: Tuerca 1/2-13 | I83: 2 | J83: 18.4
H84: Tornillo cabeza hexagonal | I84: 2 | J84: 135
H85: Total lote 1 | J85: =J6+J9+J13+J15+J17+J22+J24+J30+J32+J35+J37+J39+J43+J50+J52+J54+J63+J66+J68+J73 -> 9098.24
A87: LOTE 2 · Hidratación y comidas (Fresko)
A88: 2 | B88: L2-2 | C88: 2026-09-10 | D88: 14:18 | E88: Fresko | F88: 462 8024 22 5050 / aut 389815 | G88: Tarjeta | H88: TOTAL DEL TICKET | J88: 10
H89: Refresco Coca-Cola | I89: 1 | J89: 10
A90: 2 | B90: L2-5 | C90: 2026-09-10 | D90: 15:52 | E90: Fresko (cafetería) | F90: 462 34 54 5393 / aut 203672 | G90: Tarjeta | H90: TOTAL DEL TICKET | J90: 76
H91: Cappuccino 8 oz | I91: 1 | J91: 65
H92: Leche | I92: 1 | J92: 11
A93: 2 | B93: L2-9 | C93: 2026-09-10 | D93: 17:08 | E93: Fresko (cafetería) | F93: 462 69 53 5320 | G93: Efectivo | H93: TOTAL DEL TICKET | J93: 99
H94: Cappuccino 16 oz | I94: 1 | J94: 99
A95: 2 | B95: L2-7 | C95: 2026-09-11 | D95: 16:02 | E95: Fresko | F95: 462 54 5 5134 / aut 169745 | G95: Tarjeta | H95: TOTAL DEL TICKET | J95: 203.53
H96: Pollo entero Select (1.969 kg) | I96: 1 | J96: 70.7
H97: Flecha de res suprema (0.825 kg) | I97: 1 | J97: 132.83
A98: 2 | B98: L2-6 | C98: 2026-09-11 | D98: 16:32 | E98: Fresko | F98: 462 8024 22 5216 / aut 874145 | G98: Tarjeta | H98: TOTAL DEL TICKET | J98: 152.09
H99: Refresco Coca-Cola | I99: 1 | J99: 58.8
H100: Vasos Bio Products | I100: 1 | J100: 73
H101: Chile jalapeño (0.19 kg) | I101: 1 | J101: 4.69
H102: Tortilla de maíz (1.04 kg) | I102: 1 | J102: 15.6
...

Sheet Cargos Fresko
A1: CARGOS DE TARJETA EN FRESKO VALLE CUMBRES (estado de cuenta) — sin duplicados
A2: 54 cargos del 9 al 24-sep. 39 son las mismas compras que ya están en los tickets de los lotes (mismo monto y mismo día; en la foto del ticket se ve el pago con tarjeta), por eso no se vuelven a contar. Un cargo de $1,679.05 es el ticket L4-11 ($179.05) más un retiro de efectivo de $1,500 en caja, que no es compra. Solo se cuentan los 14 cargos que no tienen ticket en los lotes.
A4: # | B4: Fecha | C4: Comercio | D4: Importe | E4: ¿Ya está en un ticket de los lotes? | F4: Se cuenta en el cuadre
A5: 1 | B5: 2026-09-09 | C5: Fresko Valle Cumbres | D5: 10 | E5: Sí: ticket L2-2 del lote 2 (10-sep 14:18) | F5: 0
A6: 2 | B6: 2026-09-09 | C6: Fresko Valle Cumbres | D6: 29 | E6: Sí: ticket 8 del lote 1 (10-sep 20:21) | F6: 0
A7: 3 | B7: 2026-09-09 | C7: Fresko Valle Cumbres | D7: 94 | E7: Sí: ticket 10 del lote 1 (09-sep 19:02) | F7: 0
A8: 4 | B8: 2026-09-09 | C8: Fresko Valle Cumbres | D8: 99 | E8: Sí: ticket L3-1 del lote 3 (10-sep 16:11) | F8: 0
A9: 5 | B9: 2026-09-09 | C9: Fresko Valle Cumbres | D9: 113 | E9: Sí: ticket L3-7 del lote 3 (09-sep 16:02) | F9: 0
A10: 6 | B10: 2026-09-09 | C10: Fresko Valle Cumbres | D10: 122.8 | E10: No | F10: =D10 -> 122.8
A11: 7 | B11: 2026-09-09 | C11: Fresko Valle Cumbres | D11: 135.35 | E11: Sí: ticket 7 del lote 1 (09-sep 18:47) | F11: 0
A12: 8 | B12: 2026-09-10 | C12: Fresko Valle Cumbres | D12: 29 | E12: Sí: ticket 14 del lote 1 (11-sep 16:47) | F12: 0
A13: 9 | B13: 2026-09-10 | C13: Fresko Valle Cumbres | D13: 152.09 | E13: Sí: ticket L2-6 del lote 2 (11-sep 16:32) | F13: 0
A14: 10 | B14: 2026-09-10 | C14: Fresko Valle Cumbres | D14: 153 | E14: Sí: ticket L3-2 del lote 3 (10-sep 11:53) | F14: 0
A15: 11 | B15: 2026-09-10 | C15: Fresko Valle Cumbres | D15: 203.53 | E15: Sí: ticket L2-7 del lote 2 (11-sep 16:02) | F15: 0
A16: 12 | B16: 2026-09-10 | C16: Fresko Valle Cumbres | D16: 266.5 | E16: Sí: ticket L4-14 del lote 4 (11-sep 09:52) | F16: 0
A17: 13 | B17: 2026-09-10 | C17: Fresko Valle Cumbres | D17: 379.25 | E17: No | F17: =D17 -> 379.25
A18: 14 | B18: 2026-09-10 | C18: Fresko Valle Cumbres | D18: 628 | E18: No | F18: =D18 -> 628
A19: 15 | B19: 2026-09-10 | C19: Fresko Valle Cumbres | D19: 1679.05 | E19: Sí: ticket L4-11 del lote 4 ($179.05) + retiro de efectivo de $1,500 en caja (no es compra) | F19: 0
A20: 16 | B20: 2026-09-11 | C20: Fresko Valle Cumbres | D20: 56.25 | E20: No | F20: =D20 -> 56.25
A21: 17 | B21: 2026-09-11 | C21: Fresko Valle Cumbres | D21: 728 | E21: No | F21: =D21 -> 728
A22: 18 | B22: 2026-09-12 | C22: Fresko Valle Cumbres | D22: 144 | E22: Sí: ticket 3 del lote 1 (12-sep 13:33) | F22: 0
A23: 19 | B23: 2026-09-12 | C23: Fresko Valle Cumbres | D23: 372.58 | E23: No | F23: =D23 -> 372.58
A24: 20 | B24: 2026-09-13 | C24: Fresko Valle Cumbres | D24: 53.55 | E24: Sí: ticket L4-9 del lote 4 (13-sep 20:30) | F24: 0
A25: 21 | B25: 2026-09-13 | C25: Fresko Valle Cumbres | D25: 84.91 | E25: No | F25: =D25 -> 84.91
A26: 22 | B26: 2026-09-13 | C26: Fresko Valle Cumbres | D26: 89 | E26: No | F26: =D26 -> 89
A27: 23 | B27: 2026-09-13 | C27: Fresko Valle Cumbres | D27: 253.35 | E27: Sí: ticket L3-11 del lote 3 (13-sep 17:24) | F27: 0
A28: 24 | B28: 2026-09-13 | C28: Fresko Valle Cumbres | D28: 282 | E28: No | F28: =D28 -> 282
A29: 25 | B29: 2026-09-13 | C29: Fresko Valle Cumbres | D29: 321 | E29: Sí: ticket 5 del lote 1 (13-sep 18:36) | F29: 0
A30: 26 | B30: 2026-09-14 | C30: Fresko Valle Cumbres | D30: 46.5 | E30: Sí: ticket L2-1 del lote 2 (14-sep 17:23) | F30: 0
A31: 27 | B31: 2026-09-15 | C31: Fresko Valle Cumbres | D31: 78 | E31: Sí: ticket 13 del lote 1 (15-sep 15:16) | F31: 0
A32: 28 | B32: 2026-09-15 | C32: Fresko Valle Cumbres | D32: 99 | E32: Sí: ticket L3-10 del lote 3 (15-sep 14:06) | F32: 0
A33: 29 | B33: 2026-09-15 | C33: Fresko Valle Cumbres | D33: 120 | E33: Sí: ticket L3-9 del lote 3 (15-sep 17:15) | F33: 0
A34: 30 | B34: 2026-09-15 | C34: Fresko Valle Cumbres | D34: 179 | E34: Sí: ticket 4 del lote 1 (15-sep 15:08) | F34: 0
A35: 31 | B35: 2026-09-17 | C35: Fresko Valle Cumbres | D35: 33.9 | E35: Sí: ticket L2-17 del lote 2 (17-sep 16:34) | F35: 0
A36: 32 | B36: 2026-09-17 | C36: Fresko Valle Cumbres | D36: 142 | E36: Sí: ticket 18 del lote 1 (17-sep 17:06) | F36: 0
A37: 33 | B37: 2026-09-17 | C37: Fresko Valle Cumbres | D37: 275.85 | E37: Sí: ticket L4-4 del lote 4 (sin fecha en la foto) | F37: 0
A38: 34 | B38: 2026-09-18 | C38: Fresko Valle Cumbres | D38: 56 | E38: Sí: ticket L2-13 del lote 2 (18-sep 15:45) | F38: 0
A39: 35 | B39: 2026-09-18 | C39: Fresko Valle Cumbres | D39: 244.9 | E39: Sí: ticket L4-13 del lote 4 (18-sep 14:01) | F39: 0
A40: 36 | B40: 2026-09-18 | C40: Fresko Valle Cumbres | D40: 553.15 | E40: Sí: ticket L2-10 del lote 2 (17-sep 21:01) | F40: 0
A41: 37 | B41: 2026-09-19 | C41: Fresko Valle Cumbres | D41: 65 | E41: Sí: ticket L3-4 del lote 3 (19-sep 17:32) | F41: 0
A42: 38 | B42: 2026-09-19 | C42: Fresko Valle Cumbres | D42: 380 | E42: No | F42: =D42 -> 380
A43: 39 | B43: 2026-09-20 | C43: Fresko Valle Cumbres | D43: 44 | E43: Sí: ticket 19 del lote 1 (20-sep 20:32) | F43: 0
A44: 40 | B44: 2026-09-20 | C44: Fresko Valle Cumbres | D44: 248.46 | E44: Sí: ticket L2-12 del lote 2 (20-sep 19:32) | F44: 0
A45: 41 | B45: 2026-09-21 | C45: Fresko Valle Cumbres | D45: 55 | E45: Sí: ticket L2-19 del lote 2 (21-sep 15:03) | F45: 0
A46: 42 | B46: 2026-09-21 | C46: Fresko Valle Cumbres | D46: 176.8 | E46: Sí: ticket L4-10 del lote 4 (21-sep 17:35) | F46: 0
A47: 43 | B47: 2026-09-21 | C47: Fresko Valle Cumbres | D47: 196.21 | E47: Sí: ticket L2-18 del lote 2 (21-sep 15:26) | F47: 0
A48: 44 | B48: 2026-09-21 | C48: Fresko Valle Cumbres | D48: 265.4 | E48: Sí: ticket L4-8 del lote 4 (21-sep 14:09) | F48: 0
A49: 45 | B49: 2026-09-21 | C49: Fresko Valle Cumbres | D49: 287.5 | E49: No | F49: =D49 -> 287.5
A50: 46 | B50: 2026-09-22 | C50: Fresko Valle Cumbres | D50: 24 | E50: Sí: ticket 16 del lote 1 (22-sep 16:00) | F50: 0
A51: 47 | B51: 2026-09-22 | C51: Fresko Valle Cumbres | D51: 62 | E51: Sí: ticket L2-4 del lote 2 (22-sep 18:02) | F51: 0
A52: 48 | B52: 2026-09-22 | C52: Fresko Valle Cumbres | D52: 82 | E52: Sí: ticket L2-8 del lote 2 (22-sep 16:09) | F52: 0
A53: 49 | B53: 2026-09-22 | C53: Fresko Valle Cumbres | D53: 97.8 | E53: Sí: ticket L2-16 del lote 2 (22-sep 19:26) | F53: 0
A54: 50 | B54: 2026-09-22 | C54: Fresko Valle Cumbres | D54: 142 | E54: Sí: ticket L2-3 del lote 2 (22-sep 20:59) | F54: 0
A55: 51 | B55: 2026-09-22 | C55: Fresko Valle Cumbres | D55: 650.4 | E55: Sí: ticket L4-7 del lote 4 (sin fecha en la foto) | F55: 0
A56: 52 | B56: 2026-09-23 | C56: Fresko Valle Cumbres | D56: 398.5 | E56: No | F56: =D56 -> 398.5
A57: 53 | B57: 2026-09-24 | C57: Fresko Valle Cumbres | D57: 27.3 | E57: No | F57: =D57 -> 27.3
A58: 54 | B58: 2026-09-24 | C58: Fresko Valle Cumbres | D58: 148 | E58: No | F58: =D58 -> 148
C59: TOTAL | D59: =SUM(D5:D58) -> 11656.88 | E59: Se cuenta en el cuadre | F59: =SUM(F5:F58) -> 3984.09
